syara/__init__.py
syara/cache.py
syara/compiled_rules.py
syara/compiler.py
syara/config.py
syara/config.yaml
syara/models.py
syara/parser.py
syara/engine/__init__.py
syara/engine/chunker.py
syara/engine/classifier.py
syara/engine/cleaner.py
syara/engine/llm_evaluator.py
syara/engine/phash_matcher.py
syara/engine/semantic_matcher.py
syara/engine/string_matcher.py
syara-0.2.3.dist-info/licenses/LICENSE
syara-0.2.3.dist-info/METADATA
syara-0.2.3.dist-info/WHEEL
syara-0.2.3.dist-info/top_level.txt
syara-0.2.3.dist-info/RECORD
