Metadata-Version: 2.4
Name: syara
Version: 0.2.3
Summary: Semantic YARA - YARA-like rules with semantic matching, classification, and LLM evaluation
Author: nabeelxy
License: MIT
Project-URL: Homepage, https://github.com/nabeelxy/syara
Project-URL: Documentation, https://github.com/nabeelxy/syara/blob/main/README.md
Project-URL: Repository, https://github.com/nabeelxy/syara
Project-URL: Issues, https://github.com/nabeelxy/syara/issues
Keywords: yara,semantic,matching,security,llm,nlp,prompt-injection
Classifier: Development Status :: 3 - Alpha
Classifier: Intended Audience :: Developers
Classifier: Intended Audience :: Information Technology
Classifier: License :: OSI Approved :: MIT License
Classifier: Programming Language :: Python :: 3
Classifier: Programming Language :: Python :: 3.8
Classifier: Programming Language :: Python :: 3.9
Classifier: Programming Language :: Python :: 3.10
Classifier: Programming Language :: Python :: 3.11
Classifier: Programming Language :: Python :: 3.12
Classifier: Topic :: Security
Classifier: Topic :: Software Development :: Libraries :: Python Modules
Requires-Python: >=3.8
License-File: LICENSE
Requires-Dist: numpy>=1.24.0
Requires-Dist: pyyaml>=6.0
Provides-Extra: sbert
Requires-Dist: sentence-transformers>=2.2.0; extra == "sbert"
Requires-Dist: torch>=2.0.0; extra == "sbert"
Provides-Extra: classifier
Requires-Dist: sentence-transformers>=2.2.0; extra == "classifier"
Requires-Dist: torch>=2.0.0; extra == "classifier"
Requires-Dist: scikit-learn>=1.3.0; extra == "classifier"
Requires-Dist: transformers>=4.30.0; extra == "classifier"
Provides-Extra: llm
Requires-Dist: openai>=1.0.0; extra == "llm"
Requires-Dist: transformers>=4.30.0; extra == "llm"
Requires-Dist: torch>=2.0.0; extra == "llm"
Provides-Extra: all
Requires-Dist: sentence-transformers>=2.2.0; extra == "all"
Requires-Dist: torch>=2.0.0; extra == "all"
Requires-Dist: scikit-learn>=1.3.0; extra == "all"
Requires-Dist: transformers>=4.30.0; extra == "all"
Requires-Dist: openai>=1.0.0; extra == "all"
Provides-Extra: dev
Requires-Dist: pytest>=7.0.0; extra == "dev"
Requires-Dist: pytest-cov>=4.0.0; extra == "dev"
Requires-Dist: black>=23.0.0; extra == "dev"
Requires-Dist: flake8>=6.0.0; extra == "dev"
Requires-Dist: mypy>=1.0.0; extra == "dev"
Dynamic: license-file
